<annotation>
	<folder>images</folder>
	<filename>070435cd66451c9119456bb2ff97a2e9666d59a9.jpg</filename>
	<path>../Priv_personpart/images/070435cd66451c9119456bb2ff97a2e9666d59a9.jpg</path>
	<source>
		<database>Unknown</database>
	</source>
	<size>
		<width>950</width>
		<height>725</height>
		<depth>1</depth>
	</size>
	<segmented>0</segmented>
	<object>
		<name>sports ball</name>
		<pose>Unspecified</pose>
		<truncated>0</truncated>
		<difficult>0</difficult>
		<bndbox>
			<xmin>492</xmin>
			<ymin>589</ymin>
			<xmax>588</xmax>
			<ymax>690</ymax>
		</bndbox>
	</object>
	<object>
		<name>person</name>
		<pose>Unspecified</pose>
		<truncated>0</truncated>
		<difficult>0</difficult>
		<bndbox>
			<xmin>406</xmin>
			<ymin>60</ymin>
			<xmax>766</xmax>
			<ymax>657</ymax>
		</bndbox>
	</object>
	<object>
		<name>person</name>
		<pose>Unspecified</pose>
		<truncated>0</truncated>
		<difficult>0</difficult>
		<bndbox>
			<xmin>85</xmin>
			<ymin>8</ymin>
			<xmax>456</xmax>
			<ymax>694</ymax>
		</bndbox>
	</object>
	<object>
		<name>person</name>
		<pose>Unspecified</pose>
		<truncated>0</truncated>
		<difficult>0</difficult>
		<bndbox>
			<xmin>708</xmin>
			<ymin>67</ymin>
			<xmax>845</xmax>
			<ymax>482</ymax>
		</bndbox>
	</object>
</annotation>
