<annotation>
	<folder>images</folder>
	<filename>0abb6da5c3d35fcc185b026726d0785a48009d29.jpg</filename>
	<path>../Priv_personpart/images/0abb6da5c3d35fcc185b026726d0785a48009d29.jpg</path>
	<source>
		<database>Unknown</database>
	</source>
	<size>
		<width>550</width>
		<height>825</height>
		<depth>1</depth>
	</size>
	<segmented>0</segmented>
	<object>
		<name>person</name>
		<pose>Unspecified</pose>
		<truncated>0</truncated>
		<difficult>0</difficult>
		<bndbox>
			<xmin>164</xmin>
			<ymin>38</ymin>
			<xmax>390</xmax>
			<ymax>782</ymax>
		</bndbox>
	</object>
	<object>
		<name>car</name>
		<pose>Unspecified</pose>
		<truncated>0</truncated>
		<difficult>0</difficult>
		<bndbox>
			<xmin>90</xmin>
			<ymin>350</ymin>
			<xmax>175</xmax>
			<ymax>491</ymax>
		</bndbox>
	</object>
	<object>
		<name>backpack</name>
		<pose>Unspecified</pose>
		<truncated>0</truncated>
		<difficult>0</difficult>
		<bndbox>
			<xmin>88</xmin>
			<ymin>480</ymin>
			<xmax>274</xmax>
			<ymax>712</ymax>
		</bndbox>
	</object>
</annotation>
