<annotation>
	<folder>images</folder>
	<filename>19a46418b880ae3213a4c8390dff3d68ee318a86.jpg</filename>
	<path>../Priv_personpart/images/19a46418b880ae3213a4c8390dff3d68ee318a86.jpg</path>
	<source>
		<database>Unknown</database>
	</source>
	<size>
		<width>503</width>
		<height>704</height>
		<depth>1</depth>
	</size>
	<segmented>0</segmented>
	<object>
		<name>person</name>
		<pose>Unspecified</pose>
		<truncated>0</truncated>
		<difficult>0</difficult>
		<bndbox>
			<xmin>101</xmin>
			<ymin>35</ymin>
			<xmax>299</xmax>
			<ymax>687</ymax>
		</bndbox>
	</object>
	<object>
		<name>pottedplant</name>
		<pose>Unspecified</pose>
		<truncated>0</truncated>
		<difficult>0</difficult>
		<bndbox>
			<xmin>310</xmin>
			<ymin>188</ymin>
			<xmax>468</xmax>
			<ymax>360</ymax>
		</bndbox>
	</object>
</annotation>
