<annotation>
	<folder>images</folder>
	<filename>3042f656b80a923b6c51eb55dde73733f34c8e55.jpg</filename>
	<path>../Priv_personpart/images/3042f656b80a923b6c51eb55dde73733f34c8e55.jpg</path>
	<source>
		<database>Unknown</database>
	</source>
	<size>
		<width>510</width>
		<height>709</height>
		<depth>1</depth>
	</size>
	<segmented>0</segmented>
	<object>
		<name>person</name>
		<pose>Unspecified</pose>
		<truncated>0</truncated>
		<difficult>0</difficult>
		<bndbox>
			<xmin>52</xmin>
			<ymin>115</ymin>
			<xmax>472</xmax>
			<ymax>679</ymax>
		</bndbox>
	</object>
	<object>
		<name>sports ball</name>
		<pose>Unspecified</pose>
		<truncated>0</truncated>
		<difficult>0</difficult>
		<bndbox>
			<xmin>252</xmin>
			<ymin>491</ymin>
			<xmax>349</xmax>
			<ymax>611</ymax>
		</bndbox>
	</object>
	<object>
		<name>person</name>
		<pose>Unspecified</pose>
		<truncated>0</truncated>
		<difficult>0</difficult>
		<bndbox>
			<xmin>7</xmin>
			<ymin>23</ymin>
			<xmax>138</xmax>
			<ymax>625</ymax>
		</bndbox>
	</object>
	<object>
		<name>person</name>
		<pose>Unspecified</pose>
		<truncated>0</truncated>
		<difficult>0</difficult>
		<bndbox>
			<xmin>95</xmin>
			<ymin>375</ymin>
			<xmax>126</xmax>
			<ymax>453</ymax>
		</bndbox>
	</object>
	<object>
		<name>person</name>
		<pose>Unspecified</pose>
		<truncated>0</truncated>
		<difficult>0</difficult>
		<bndbox>
			<xmin>70</xmin>
			<ymin>379</ymin>
			<xmax>98</xmax>
			<ymax>450</ymax>
		</bndbox>
	</object>
</annotation>
