<annotation>
	<folder>images</folder>
	<filename>6a932ba79fabba771a00c3b676225718e0c78464.jpg</filename>
	<path>../Priv_personpart/images/6a932ba79fabba771a00c3b676225718e0c78464.jpg</path>
	<source>
		<database>Unknown</database>
	</source>
	<size>
		<width>894</width>
		<height>596</height>
		<depth>1</depth>
	</size>
	<segmented>0</segmented>
	<object>
		<name>person</name>
		<pose>Unspecified</pose>
		<truncated>0</truncated>
		<difficult>0</difficult>
		<bndbox>
			<xmin>238</xmin>
			<ymin>94</ymin>
			<xmax>582</xmax>
			<ymax>595</ymax>
		</bndbox>
	</object>
	<object>
		<name>person</name>
		<pose>Unspecified</pose>
		<truncated>0</truncated>
		<difficult>0</difficult>
		<bndbox>
			<xmin>188</xmin>
			<ymin>186</ymin>
			<xmax>392</xmax>
			<ymax>595</ymax>
		</bndbox>
	</object>
	<object>
		<name>person</name>
		<pose>Unspecified</pose>
		<truncated>0</truncated>
		<difficult>0</difficult>
		<bndbox>
			<xmin>486</xmin>
			<ymin>2</ymin>
			<xmax>876</xmax>
			<ymax>520</ymax>
		</bndbox>
	</object>
	<object>
		<name>person</name>
		<pose>Unspecified</pose>
		<truncated>0</truncated>
		<difficult>0</difficult>
		<bndbox>
			<xmin>262</xmin>
			<ymin>24</ymin>
			<xmax>414</xmax>
			<ymax>566</ymax>
		</bndbox>
	</object>
</annotation>
