<annotation>
	<folder>images</folder>
	<filename>799d654a1c370b3ed1e4f09ae68bddd72d19e873.jpg</filename>
	<path>../Priv_personpart/images/799d654a1c370b3ed1e4f09ae68bddd72d19e873.jpg</path>
	<source>
		<database>Unknown</database>
	</source>
	<size>
		<width>800</width>
		<height>582</height>
		<depth>1</depth>
	</size>
	<segmented>0</segmented>
	<object>
		<name>person</name>
		<pose>Unspecified</pose>
		<truncated>0</truncated>
		<difficult>0</difficult>
		<bndbox>
			<xmin>25</xmin>
			<ymin>29</ymin>
			<xmax>286</xmax>
			<ymax>568</ymax>
		</bndbox>
	</object>
	<object>
		<name>person</name>
		<pose>Unspecified</pose>
		<truncated>0</truncated>
		<difficult>0</difficult>
		<bndbox>
			<xmin>743</xmin>
			<ymin>0</ymin>
			<xmax>798</xmax>
			<ymax>413</ymax>
		</bndbox>
	</object>
	<object>
		<name>person</name>
		<pose>Unspecified</pose>
		<truncated>0</truncated>
		<difficult>0</difficult>
		<bndbox>
			<xmin>382</xmin>
			<ymin>29</ymin>
			<xmax>659</xmax>
			<ymax>571</ymax>
		</bndbox>
	</object>
	<object>
		<name>cell phone</name>
		<pose>Unspecified</pose>
		<truncated>0</truncated>
		<difficult>0</difficult>
		<bndbox>
			<xmin>367</xmin>
			<ymin>227</ymin>
			<xmax>454</xmax>
			<ymax>263</ymax>
		</bndbox>
	</object>
</annotation>
