<annotation>
	<folder>images</folder>
	<filename>8ab22626152b113ee40958efff9ebf7c703dddf9.jpg</filename>
	<path>../Priv_personpart/images/8ab22626152b113ee40958efff9ebf7c703dddf9.jpg</path>
	<source>
		<database>Unknown</database>
	</source>
	<size>
		<width>550</width>
		<height>825</height>
		<depth>1</depth>
	</size>
	<segmented>0</segmented>
	<object>
		<name>person</name>
		<pose>Unspecified</pose>
		<truncated>0</truncated>
		<difficult>0</difficult>
		<bndbox>
			<xmin>7</xmin>
			<ymin>209</ymin>
			<xmax>206</xmax>
			<ymax>795</ymax>
		</bndbox>
	</object>
	<object>
		<name>person</name>
		<pose>Unspecified</pose>
		<truncated>0</truncated>
		<difficult>0</difficult>
		<bndbox>
			<xmin>351</xmin>
			<ymin>43</ymin>
			<xmax>549</xmax>
			<ymax>764</ymax>
		</bndbox>
	</object>
</annotation>
