<annotation>
	<folder>images</folder>
	<filename>bbf7b007a4b62e9477077faab1cccc9648cc51d4.jpg</filename>
	<path>../Priv_personpart/images/bbf7b007a4b62e9477077faab1cccc9648cc51d4.jpg</path>
	<source>
		<database>Unknown</database>
	</source>
	<size>
		<width>550</width>
		<height>721</height>
		<depth>1</depth>
	</size>
	<segmented>0</segmented>
	<object>
		<name>person</name>
		<pose>Unspecified</pose>
		<truncated>0</truncated>
		<difficult>0</difficult>
		<bndbox>
			<xmin>159</xmin>
			<ymin>126</ymin>
			<xmax>446</xmax>
			<ymax>714</ymax>
		</bndbox>
	</object>
	<object>
		<name>car</name>
		<pose>Unspecified</pose>
		<truncated>0</truncated>
		<difficult>0</difficult>
		<bndbox>
			<xmin>400</xmin>
			<ymin>278</ymin>
			<xmax>449</xmax>
			<ymax>351</ymax>
		</bndbox>
	</object>
	<object>
		<name>pottedplant</name>
		<pose>Unspecified</pose>
		<truncated>0</truncated>
		<difficult>0</difficult>
		<bndbox>
			<xmin>97</xmin>
			<ymin>541</ymin>
			<xmax>161</xmax>
			<ymax>648</ymax>
		</bndbox>
	</object>
	<object>
		<name>pottedplant</name>
		<pose>Unspecified</pose>
		<truncated>0</truncated>
		<difficult>0</difficult>
		<bndbox>
			<xmin>52</xmin>
			<ymin>557</ymin>
			<xmax>107</xmax>
			<ymax>675</ymax>
		</bndbox>
	</object>
	<object>
		<name>car</name>
		<pose>Unspecified</pose>
		<truncated>0</truncated>
		<difficult>0</difficult>
		<bndbox>
			<xmin>6</xmin>
			<ymin>288</ymin>
			<xmax>144</xmax>
			<ymax>339</ymax>
		</bndbox>
	</object>
	<object>
		<name>car</name>
		<pose>Unspecified</pose>
		<truncated>0</truncated>
		<difficult>0</difficult>
		<bndbox>
			<xmin>424</xmin>
			<ymin>245</ymin>
			<xmax>549</xmax>
			<ymax>395</ymax>
		</bndbox>
	</object>
</annotation>
