<annotation>
	<folder>images</folder>
	<filename>bfeb253216d79eda0de6f4887074dc36f9f60e17.jpg</filename>
	<path>../Priv_personpart/images/bfeb253216d79eda0de6f4887074dc36f9f60e17.jpg</path>
	<source>
		<database>Unknown</database>
	</source>
	<size>
		<width>550</width>
		<height>825</height>
		<depth>1</depth>
	</size>
	<segmented>0</segmented>
	<object>
		<name>person</name>
		<pose>Unspecified</pose>
		<truncated>0</truncated>
		<difficult>0</difficult>
		<bndbox>
			<xmin>38</xmin>
			<ymin>105</ymin>
			<xmax>429</xmax>
			<ymax>811</ymax>
		</bndbox>
	</object>
	<object>
		<name>toothbrush</name>
		<pose>Unspecified</pose>
		<truncated>0</truncated>
		<difficult>0</difficult>
		<bndbox>
			<xmin>265</xmin>
			<ymin>251</ymin>
			<xmax>337</xmax>
			<ymax>392</ymax>
		</bndbox>
	</object>
</annotation>
