<annotation>
	<folder>images</folder>
	<filename>c85fd240dc667f5f33ef5d0d2e0e00c0b27d79c6.jpg</filename>
	<path>../Priv_personpart/images/c85fd240dc667f5f33ef5d0d2e0e00c0b27d79c6.jpg</path>
	<source>
		<database>Unknown</database>
	</source>
	<size>
		<width>550</width>
		<height>820</height>
		<depth>1</depth>
	</size>
	<segmented>0</segmented>
	<object>
		<name>person</name>
		<pose>Unspecified</pose>
		<truncated>0</truncated>
		<difficult>0</difficult>
		<bndbox>
			<xmin>95</xmin>
			<ymin>40</ymin>
			<xmax>461</xmax>
			<ymax>819</ymax>
		</bndbox>
	</object>
	<object>
		<name>cell phone</name>
		<pose>Unspecified</pose>
		<truncated>0</truncated>
		<difficult>0</difficult>
		<bndbox>
			<xmin>406</xmin>
			<ymin>342</ymin>
			<xmax>457</xmax>
			<ymax>361</ymax>
		</bndbox>
	</object>
	<object>
		<name>handbag</name>
		<pose>Unspecified</pose>
		<truncated>0</truncated>
		<difficult>0</difficult>
		<bndbox>
			<xmin>86</xmin>
			<ymin>356</ymin>
			<xmax>209</xmax>
			<ymax>638</ymax>
		</bndbox>
	</object>
</annotation>
