<annotation>
	<folder>images</folder>
	<filename>d8ce1e6be44fd2e56b46eccbab199fae64849c11.jpg</filename>
	<path>../Priv_personpart/images/d8ce1e6be44fd2e56b46eccbab199fae64849c11.jpg</path>
	<source>
		<database>Unknown</database>
	</source>
	<size>
		<width>500</width>
		<height>727</height>
		<depth>1</depth>
	</size>
	<segmented>0</segmented>
	<object>
		<name>person</name>
		<pose>Unspecified</pose>
		<truncated>0</truncated>
		<difficult>0</difficult>
		<bndbox>
			<xmin>55</xmin>
			<ymin>32</ymin>
			<xmax>216</xmax>
			<ymax>726</ymax>
		</bndbox>
	</object>
	<object>
		<name>person</name>
		<pose>Unspecified</pose>
		<truncated>0</truncated>
		<difficult>0</difficult>
		<bndbox>
			<xmin>196</xmin>
			<ymin>53</ymin>
			<xmax>360</xmax>
			<ymax>726</ymax>
		</bndbox>
	</object>
	<object>
		<name>person</name>
		<pose>Unspecified</pose>
		<truncated>1</truncated>
		<difficult>0</difficult>
		<bndbox>
			<xmin>1</xmin>
			<ymin>246</ymin>
			<xmax>68</xmax>
			<ymax>617</ymax>
		</bndbox>
	</object>
	<object>
		<name>tie</name>
		<pose>Unspecified</pose>
		<truncated>0</truncated>
		<difficult>0</difficult>
		<bndbox>
			<xmin>285</xmin>
			<ymin>208</ymin>
			<xmax>312</xmax>
			<ymax>305</ymax>
		</bndbox>
	</object>
	<object>
		<name>person</name>
		<pose>Unspecified</pose>
		<truncated>0</truncated>
		<difficult>0</difficult>
		<bndbox>
			<xmin>164</xmin>
			<ymin>512</ymin>
			<xmax>207</xmax>
			<ymax>614</ymax>
		</bndbox>
	</object>
</annotation>
