<annotation>
	<folder>images</folder>
	<filename>d965f03de7bf3f2b0482935f432230309f82ecfd.jpg</filename>
	<path>../Priv_personpart/images/d965f03de7bf3f2b0482935f432230309f82ecfd.jpg</path>
	<source>
		<database>Unknown</database>
	</source>
	<size>
		<width>500</width>
		<height>330</height>
		<depth>1</depth>
	</size>
	<segmented>0</segmented>
	<object>
		<name>person</name>
		<pose>Unspecified</pose>
		<truncated>0</truncated>
		<difficult>0</difficult>
		<bndbox>
			<xmin>208</xmin>
			<ymin>57</ymin>
			<xmax>391</xmax>
			<ymax>317</ymax>
		</bndbox>
	</object>
	<object>
		<name>person</name>
		<pose>Unspecified</pose>
		<truncated>0</truncated>
		<difficult>0</difficult>
		<bndbox>
			<xmin>30</xmin>
			<ymin>59</ymin>
			<xmax>222</xmax>
			<ymax>328</ymax>
		</bndbox>
	</object>
</annotation>
