<annotation>
	<folder>images</folder>
	<filename>d9e9fe6bc4dc742992e2d5b16109c394496d1d6f.jpg</filename>
	<path>../Priv_personpart/images/d9e9fe6bc4dc742992e2d5b16109c394496d1d6f.jpg</path>
	<source>
		<database>Unknown</database>
	</source>
	<size>
		<width>510</width>
		<height>765</height>
		<depth>1</depth>
	</size>
	<segmented>0</segmented>
	<object>
		<name>person</name>
		<pose>Unspecified</pose>
		<truncated>0</truncated>
		<difficult>0</difficult>
		<bndbox>
			<xmin>123</xmin>
			<ymin>253</ymin>
			<xmax>447</xmax>
			<ymax>690</ymax>
		</bndbox>
	</object>
	<object>
		<name>motorbike</name>
		<pose>Unspecified</pose>
		<truncated>0</truncated>
		<difficult>0</difficult>
		<bndbox>
			<xmin>103</xmin>
			<ymin>460</ymin>
			<xmax>461</xmax>
			<ymax>764</ymax>
		</bndbox>
	</object>
	<object>
		<name>person</name>
		<pose>Unspecified</pose>
		<truncated>0</truncated>
		<difficult>0</difficult>
		<bndbox>
			<xmin>111</xmin>
			<ymin>103</ymin>
			<xmax>428</xmax>
			<ymax>523</ymax>
		</bndbox>
	</object>
	<object>
		<name>bicycle</name>
		<pose>Unspecified</pose>
		<truncated>0</truncated>
		<difficult>0</difficult>
		<bndbox>
			<xmin>103</xmin>
			<ymin>460</ymin>
			<xmax>461</xmax>
			<ymax>764</ymax>
		</bndbox>
	</object>
</annotation>
