<annotation>
	<folder>images</folder>
	<filename>ed71f897e8998814a3334d89c401c845ab949e84.jpg</filename>
	<path>../Priv_personpart/images/ed71f897e8998814a3334d89c401c845ab949e84.jpg</path>
	<source>
		<database>Unknown</database>
	</source>
	<size>
		<width>500</width>
		<height>666</height>
		<depth>1</depth>
	</size>
	<segmented>0</segmented>
	<object>
		<name>person</name>
		<pose>Unspecified</pose>
		<truncated>0</truncated>
		<difficult>0</difficult>
		<bndbox>
			<xmin>28</xmin>
			<ymin>0</ymin>
			<xmax>483</xmax>
			<ymax>665</ymax>
		</bndbox>
	</object>
</annotation>
