<annotation>
  <folder>c</folder>
  <filename>0f8bb6f381d545e91a958451950f471ab5fbe5aa</filename>
  <path>C:\Users\Administrator\Desktop\chm\c\0f8bb6f381d545e91a958451950f471ab5fbe5aa.jpg</path>
  <source>
    <database>Unknown</database>
  </source>
  <size>
    <width>550</width>
    <height>825</height>
    <depth>3</depth>
  </size>
  <segmented>0</segmented>
  <shape_type>RECT</shape_type>
  <object>
    <name>person</name>
    <pose>Unspecified</pose>
    <truncated>0</truncated>
    <difficult>0</difficult>
    <bndbox>
      <xmin>191</xmin>
      <ymin>123</ymin>
      <xmax>521</xmax>
      <ymax>824</ymax>
    </bndbox>
  </object>
  <object>
    <name>face</name>
    <pose>Unspecified</pose>
    <truncated>0</truncated>
    <difficult>0</difficult>
    <bndbox>
      <xmin>279</xmin>
      <ymin>159</ymin>
      <xmax>350</xmax>
      <ymax>263</ymax>
    </bndbox>
  </object>
  </annotation>