<annotation>
  <folder>e</folder>
  <filename>34aad91bb4d5035ee36e7b8c44e6b6d6435d8ec3</filename>
  <path>C:\Users\priv_data2\Desktop\gy\e\34aad91bb4d5035ee36e7b8c44e6b6d6435d8ec3.jpg</path>
  <source>
    <database>Unknown</database>
  </source>
  <size>
    <width>666</width>
    <height>1000</height>
    <depth>3</depth>
  </size>
  <segmented>0</segmented>
  <shape_type>RECT</shape_type>
  <object>
    <name>person</name>
    <pose>Unspecified</pose>
    <truncated>0</truncated>
    <difficult>0</difficult>
    <bndbox>
      <xmin>163</xmin>
      <ymin>50</ymin>
      <xmax>447</xmax>
      <ymax>999</ymax>
    </bndbox>
  </object>
  <object>
    <name>face</name>
    <pose>Unspecified</pose>
    <truncated>0</truncated>
    <difficult>0</difficult>
    <bndbox>
      <xmin>347</xmin>
      <ymin>106</ymin>
      <xmax>419</xmax>
      <ymax>206</ymax>
    </bndbox>
  </object>
  </annotation>