<annotation>
  <folder>b</folder>
  <filename>3aa0a718182ce3bdba16fc54c8ffd4e42d755b1d</filename>
  <path>C:\Users\www\Desktop\xx\b\3aa0a718182ce3bdba16fc54c8ffd4e42d755b1d.jpg</path>
  <source>
    <database>Unknown</database>
  </source>
  <size>
    <width>700</width>
    <height>573</height>
    <depth>3</depth>
  </size>
  <segmented>0</segmented>
  <shape_type>RECT</shape_type>
  <object>
    <name>person</name>
    <pose>Unspecified</pose>
    <truncated>0</truncated>
    <difficult>0</difficult>
    <bndbox>
      <xmin>253</xmin>
      <ymin>283</ymin>
      <xmax>486</xmax>
      <ymax>675</ymax>
    </bndbox>
  </object>
  <object>
    <name>person</name>
    <pose>Unspecified</pose>
    <truncated>0</truncated>
    <difficult>0</difficult>
    <bndbox>
      <xmin>180</xmin>
      <ymin>124</ymin>
      <xmax>549</xmax>
      <ymax>588</ymax>
    </bndbox>
  </object>
  <object>
    <name>person</name>
    <pose>Unspecified</pose>
    <truncated>0</truncated>
    <difficult>0</difficult>
    <bndbox>
      <xmin>24</xmin>
      <ymin>74</ymin>
      <xmax>326</xmax>
      <ymax>538</ymax>
    </bndbox>
  </object>
  <object>
    <name>person</name>
    <pose>Unspecified</pose>
    <truncated>0</truncated>
    <difficult>0</difficult>
    <bndbox>
      <xmin>165</xmin>
      <ymin>172</ymin>
      <xmax>435</xmax>
      <ymax>660</ymax>
    </bndbox>
  </object>
  <object>
    <name>face</name>
    <pose>Unspecified</pose>
    <truncated>0</truncated>
    <difficult>0</difficult>
    <bndbox>
      <xmin>145</xmin>
      <ymin>95</ymin>
      <xmax>191</xmax>
      <ymax>146</ymax>
    </bndbox>
  </object>
  <object>
    <name>face</name>
    <pose>Unspecified</pose>
    <truncated>0</truncated>
    <difficult>0</difficult>
    <bndbox>
      <xmin>292</xmin>
      <ymin>196</ymin>
      <xmax>331</xmax>
      <ymax>247</ymax>
    </bndbox>
  </object>
  <object>
    <name>face</name>
    <pose>Unspecified</pose>
    <truncated>0</truncated>
    <difficult>0</difficult>
    <bndbox>
      <xmin>439</xmin>
      <ymin>184</ymin>
      <xmax>482</xmax>
      <ymax>235</ymax>
    </bndbox>
  </object>
  </annotation>