<annotation>
  <folder>b</folder>
  <filename>3b9367eccd1b9eeb43d2d5ac850420b5bc95d0a3</filename>
  <path>C:\Users\www\Desktop\xx\b\3b9367eccd1b9eeb43d2d5ac850420b5bc95d0a3.jpg</path>
  <source>
    <database>Unknown</database>
  </source>
  <size>
    <width>1000</width>
    <height>666</height>
    <depth>3</depth>
  </size>
  <segmented>0</segmented>
  <shape_type>RECT</shape_type>
  <object>
    <name>person</name>
    <pose>Unspecified</pose>
    <truncated>0</truncated>
    <difficult>0</difficult>
    <bndbox>
      <xmin>31</xmin>
      <ymin>105</ymin>
      <xmax>471</xmax>
      <ymax>999</ymax>
    </bndbox>
  </object>
  <object>
    <name>face</name>
    <pose>Unspecified</pose>
    <truncated>0</truncated>
    <difficult>0</difficult>
    <bndbox>
      <xmin>149</xmin>
      <ymin>181</ymin>
      <xmax>236</xmax>
      <ymax>275</ymax>
    </bndbox>
  </object>
  </annotation>