<annotation>
  <folder>a</folder>
  <filename>3bb361ad2fb8fe359387b11d7f33776e56d47b4d</filename>
  <path>C:\Users\priv_data4\Desktop\tt\a\3bb361ad2fb8fe359387b11d7f33776e56d47b4d.jpg</path>
  <source>
    <database>Unknown</database>
  </source>
  <size>
    <width>614</width>
    <height>1000</height>
    <depth>3</depth>
  </size>
  <segmented>0</segmented>
  <shape_type>RECT</shape_type>
  <object>
    <name>person</name>
    <pose>Unspecified</pose>
    <truncated>0</truncated>
    <difficult>0</difficult>
    <bndbox>
      <xmin>116</xmin>
      <ymin>82</ymin>
      <xmax>451</xmax>
      <ymax>990</ymax>
    </bndbox>
  </object>
  <object>
    <name>face</name>
    <pose>Unspecified</pose>
    <truncated>0</truncated>
    <difficult>0</difficult>
    <bndbox>
      <xmin>276</xmin>
      <ymin>124</ymin>
      <xmax>333</xmax>
      <ymax>211</ymax>
    </bndbox>
  </object>
  </annotation>