<annotation>
  <folder>a</folder>
  <filename>51e735fd4734b5f3254c07234b1e4f18a97d5db9</filename>
  <path>C:\Users\priv_data4\Desktop\tt\a\51e735fd4734b5f3254c07234b1e4f18a97d5db9.jpg</path>
  <source>
    <database>Unknown</database>
  </source>
  <size>
    <width>927</width>
    <height>600</height>
    <depth>3</depth>
  </size>
  <segmented>0</segmented>
  <shape_type>RECT</shape_type>
  <object>
    <name>person</name>
    <pose>Unspecified</pose>
    <truncated>0</truncated>
    <difficult>0</difficult>
    <bndbox>
      <xmin>461</xmin>
      <ymin>2</ymin>
      <xmax>784</xmax>
      <ymax>540</ymax>
    </bndbox>
  </object>
  <object>
    <name>person</name>
    <pose>Unspecified</pose>
    <truncated>0</truncated>
    <difficult>0</difficult>
    <bndbox>
      <xmin>263</xmin>
      <ymin>1</ymin>
      <xmax>616</xmax>
      <ymax>548</ymax>
    </bndbox>
  </object>
  <object>
    <name>person</name>
    <pose>Unspecified</pose>
    <truncated>0</truncated>
    <difficult>0</difficult>
    <bndbox>
      <xmin>276</xmin>
      <ymin>1</ymin>
      <xmax>773</xmax>
      <ymax>577</ymax>
    </bndbox>
  </object>
  <object>
    <name>face</name>
    <pose>Unspecified</pose>
    <truncated>0</truncated>
    <difficult>0</difficult>
    <bndbox>
      <xmin>295</xmin>
      <ymin>26</ymin>
      <xmax>365</xmax>
      <ymax>104</ymax>
    </bndbox>
  </object>
  <object>
    <name>face</name>
    <pose>Unspecified</pose>
    <truncated>0</truncated>
    <difficult>0</difficult>
    <bndbox>
      <xmin>625</xmin>
      <ymin>2</ymin>
      <xmax>668</xmax>
      <ymax>20</ymax>
    </bndbox>
  </object>
  <object>
    <name>person</name>
    <pose>Unspecified</pose>
    <truncated>0</truncated>
    <difficult>0</difficult>
    <bndbox>
      <xmin>1</xmin>
      <ymin>314</ymin>
      <xmax>116</xmax>
      <ymax>549</ymax>
    </bndbox>
  </object>
  </annotation>