<annotation>
  <folder>e</folder>
  <filename>566f0897e4ce4b3d3b80fa2599ee38de5f91f77e</filename>
  <path>C:\Users\priv_data2\Desktop\gy\e\566f0897e4ce4b3d3b80fa2599ee38de5f91f77e.jpg</path>
  <source>
    <database>Unknown</database>
  </source>
  <size>
    <width>900</width>
    <height>705</height>
    <depth>3</depth>
  </size>
  <segmented>0</segmented>
  <shape_type>RECT</shape_type>
  <object>
    <name>person</name>
    <pose>Unspecified</pose>
    <truncated>0</truncated>
    <difficult>0</difficult>
    <bndbox>
      <xmin>274</xmin>
      <ymin>113</ymin>
      <xmax>800</xmax>
      <ymax>704</ymax>
    </bndbox>
  </object>
  <object>
    <name>person</name>
    <pose>Unspecified</pose>
    <truncated>0</truncated>
    <difficult>0</difficult>
    <bndbox>
      <xmin>1</xmin>
      <ymin>1</ymin>
      <xmax>363</xmax>
      <ymax>650</ymax>
    </bndbox>
  </object>
  <object>
    <name>face</name>
    <pose>Unspecified</pose>
    <truncated>0</truncated>
    <difficult>0</difficult>
    <bndbox>
      <xmin>178</xmin>
      <ymin>19</ymin>
      <xmax>251</xmax>
      <ymax>129</ymax>
    </bndbox>
  </object>
  <object>
    <name>face</name>
    <pose>Unspecified</pose>
    <truncated>0</truncated>
    <difficult>0</difficult>
    <bndbox>
      <xmin>617</xmin>
      <ymin>183</ymin>
      <xmax>679</xmax>
      <ymax>280</ymax>
    </bndbox>
  </object>
  </annotation>