<annotation>
  <folder>c</folder>
  <filename>590cbfdc5c9ad5163c457ac6cec16fa55a6d512b</filename>
  <path>C:\Users\Administrator\Desktop\chm\c\590cbfdc5c9ad5163c457ac6cec16fa55a6d512b.jpg</path>
  <source>
    <database>Unknown</database>
  </source>
  <size>
    <width>500</width>
    <height>750</height>
    <depth>3</depth>
  </size>
  <segmented>0</segmented>
  <shape_type>RECT</shape_type>
  <object>
    <name>person</name>
    <pose>Unspecified</pose>
    <truncated>0</truncated>
    <difficult>0</difficult>
    <bndbox>
      <xmin>102</xmin>
      <ymin>32</ymin>
      <xmax>326</xmax>
      <ymax>734</ymax>
    </bndbox>
  </object>
  <object>
    <name>face</name>
    <pose>Unspecified</pose>
    <truncated>0</truncated>
    <difficult>0</difficult>
    <bndbox>
      <xmin>240</xmin>
      <ymin>57</ymin>
      <xmax>291</xmax>
      <ymax>142</ymax>
    </bndbox>
  </object>
</annotation>