<annotation>
  <folder>c</folder>
  <filename>881ed762227c70c66c66ea1f1944cd660dc5e5de</filename>
  <path>C:\Users\Administrator\Desktop\chm\c\881ed762227c70c66c66ea1f1944cd660dc5e5de.jpg</path>
  <source>
    <database>Unknown</database>
  </source>
  <size>
    <width>666</width>
    <height>1000</height>
    <depth>3</depth>
  </size>
  <segmented>0</segmented>
  <shape_type>RECT</shape_type>
  <object>
    <name>person</name>
    <pose>Unspecified</pose>
    <truncated>0</truncated>
    <difficult>0</difficult>
    <bndbox>
      <xmin>161</xmin>
      <ymin>21</ymin>
      <xmax>470</xmax>
      <ymax>978</ymax>
    </bndbox>
  </object>
  <object>
    <name>face</name>
    <pose>Unspecified</pose>
    <truncated>0</truncated>
    <difficult>0</difficult>
    <bndbox>
      <xmin>290</xmin>
      <ymin>50</ymin>
      <xmax>366</xmax>
      <ymax>149</ymax>
    </bndbox>
  </object>
</annotation>