<annotation>
  <folder>facehand_error</folder>
  <filename>9092e56d560767e8c6de23cfbed2d3874077ca0d</filename>
  <path>C:\Users\priv_data4\Desktop\facehand_error\facehand_error\9092e56d560767e8c6de23cfbed2d3874077ca0d.jpg</path>
  <source>
    <database>Unknown</database>
  </source>
  <size>
    <width>500</width>
    <height>773</height>
    <depth>3</depth>
  </size>
  <segmented>0</segmented>
  <shape_type>RECT</shape_type>
  <object>
    <name>person</name>
    <pose>Unspecified</pose>
    <truncated>0</truncated>
    <difficult>0</difficult>
    <bndbox>
      <xmin>51</xmin>
      <ymin>4</ymin>
      <xmax>336</xmax>
      <ymax>746</ymax>
    </bndbox>
  </object>
  <object>
    <name>person</name>
    <pose>Unspecified</pose>
    <truncated>0</truncated>
    <difficult>0</difficult>
    <bndbox>
      <xmin>224</xmin>
      <ymin>20</ymin>
      <xmax>438</xmax>
      <ymax>771</ymax>
    </bndbox>
  </object>
  <object>
    <name>face</name>
    <pose>Unspecified</pose>
    <truncated>0</truncated>
    <difficult>0</difficult>
    <bndbox>
      <xmin>161</xmin>
      <ymin>37</ymin>
      <xmax>225</xmax>
      <ymax>132</ymax>
    </bndbox>
  </object>
  <object>
    <name>face</name>
    <pose>Unspecified</pose>
    <truncated>0</truncated>
    <difficult>0</difficult>
    <bndbox>
      <xmin>272</xmin>
      <ymin>55</ymin>
      <xmax>340</xmax>
      <ymax>144</ymax>
    </bndbox>
  </object>
  <object>
    <name>person</name>
    <pose>Unspecified</pose>
    <truncated>0</truncated>
    <difficult>0</difficult>
    <bndbox>
      <xmin>1</xmin>
      <ymin>2</ymin>
      <xmax>57</xmax>
      <ymax>268</ymax>
    </bndbox>
  </object>
  <object>
    <name>person</name>
    <pose>Unspecified</pose>
    <truncated>0</truncated>
    <difficult>0</difficult>
    <bndbox>
      <xmin>24</xmin>
      <ymin>1</ymin>
      <xmax>122</xmax>
      <ymax>273</ymax>
    </bndbox>
  </object>
</annotation>