<annotation>
  <folder>a</folder>
  <filename>bab5e9748b539f304155018e2a78dabb88b63dcc</filename>
  <path>C:\Users\priv_data4\Desktop\tt\a\bab5e9748b539f304155018e2a78dabb88b63dcc.jpg</path>
  <source>
    <database>Unknown</database>
  </source>
  <size>
    <width>1000</width>
    <height>713</height>
    <depth>3</depth>
  </size>
  <segmented>0</segmented>
  <shape_type>RECT</shape_type>
  <object>
    <name>person</name>
    <pose>Unspecified</pose>
    <truncated>0</truncated>
    <difficult>0</difficult>
    <bndbox>
      <xmin>487</xmin>
      <ymin>198</ymin>
      <xmax>998</xmax>
      <ymax>712</ymax>
    </bndbox>
  </object>
  <object>
    <name>person</name>
    <pose>Unspecified</pose>
    <truncated>0</truncated>
    <difficult>0</difficult>
    <bndbox>
      <xmin>441</xmin>
      <ymin>14</ymin>
      <xmax>717</xmax>
      <ymax>462</ymax>
    </bndbox>
  </object>
  <object>
    <name>person</name>
    <pose>Unspecified</pose>
    <truncated>0</truncated>
    <difficult>0</difficult>
    <bndbox>
      <xmin>122</xmin>
      <ymin>38</ymin>
      <xmax>425</xmax>
      <ymax>458</ymax>
    </bndbox>
  </object>
  <object>
    <name>face</name>
    <pose>Unspecified</pose>
    <truncated>0</truncated>
    <difficult>0</difficult>
    <bndbox>
      <xmin>173</xmin>
      <ymin>158</ymin>
      <xmax>273</xmax>
      <ymax>243</ymax>
    </bndbox>
  </object>
  <object>
    <name>face</name>
    <pose>Unspecified</pose>
    <truncated>0</truncated>
    <difficult>0</difficult>
    <bndbox>
      <xmin>541</xmin>
      <ymin>148</ymin>
      <xmax>637</xmax>
      <ymax>209</ymax>
    </bndbox>
  </object>
  <object>
    <name>face</name>
    <pose>Unspecified</pose>
    <truncated>0</truncated>
    <difficult>0</difficult>
    <bndbox>
      <xmin>717</xmin>
      <ymin>315</ymin>
      <xmax>780</xmax>
      <ymax>459</ymax>
    </bndbox>
  </object>
  </annotation>