<annotation>
  <folder>a</folder>
  <filename>bb48dcc305ea91ebef3960bd39d63dd4c7c434f6</filename>
  <path>C:\Users\priv_data4\Desktop\tt\a\bb48dcc305ea91ebef3960bd39d63dd4c7c434f6.jpg</path>
  <source>
    <database>Unknown</database>
  </source>
  <size>
    <width>550</width>
    <height>778</height>
    <depth>3</depth>
  </size>
  <segmented>0</segmented>
  <shape_type>RECT</shape_type>
  <object>
    <name>person</name>
    <pose>Unspecified</pose>
    <truncated>0</truncated>
    <difficult>0</difficult>
    <bndbox>
      <xmin>23</xmin>
      <ymin>27</ymin>
      <xmax>466</xmax>
      <ymax>736</ymax>
    </bndbox>
  </object>
  <object>
    <name>face</name>
    <pose>Unspecified</pose>
    <truncated>0</truncated>
    <difficult>0</difficult>
    <bndbox>
      <xmin>286</xmin>
      <ymin>122</ymin>
      <xmax>354</xmax>
      <ymax>215</ymax>
    </bndbox>
  </object>
  </annotation>