<annotation>
  <folder>f</folder>
  <filename>bbb084d7b1bf205696cce7fc84daa819823ac1cc</filename>
  <path>C:\Users\asus\Desktop\handface\f\bbb084d7b1bf205696cce7fc84daa819823ac1cc.jpg</path>
  <source>
    <database>Unknown</database>
  </source>
  <size>
    <width>533</width>
    <height>800</height>
    <depth>3</depth>
  </size>
  <segmented>0</segmented>
  <shape_type>RECT</shape_type>
  <object>
    <name>person</name>
    <pose>Unspecified</pose>
    <truncated>0</truncated>
    <difficult>0</difficult>
    <bndbox>
      <xmin>323</xmin>
      <ymin>44</ymin>
      <xmax>690</xmax>
      <ymax>525</ymax>
    </bndbox>
  </object>
  <object>
    <name>face</name>
    <pose>Unspecified</pose>
    <truncated>0</truncated>
    <difficult>0</difficult>
    <bndbox>
      <xmin>539</xmin>
      <ymin>73</ymin>
      <xmax>613</xmax>
      <ymax>183</ymax>
    </bndbox>
  </object>
  </annotation>