<annotation>
  <folder>a</folder>
  <filename>cdf87e6a5844ab365167a2a58b7127212d4faca6</filename>
  <path>C:\Users\priv_data4\Desktop\tt\a\cdf87e6a5844ab365167a2a58b7127212d4faca6.jpg</path>
  <source>
    <database>Unknown</database>
  </source>
  <size>
    <width>694</width>
    <height>1000</height>
    <depth>3</depth>
  </size>
  <segmented>0</segmented>
  <shape_type>RECT</shape_type>
  <object>
    <name>person</name>
    <pose>Unspecified</pose>
    <truncated>0</truncated>
    <difficult>0</difficult>
    <bndbox>
      <xmin>6</xmin>
      <ymin>93</ymin>
      <xmax>693</xmax>
      <ymax>996</ymax>
    </bndbox>
  </object>
  <object>
    <name>face</name>
    <pose>Unspecified</pose>
    <truncated>0</truncated>
    <difficult>0</difficult>
    <bndbox>
      <xmin>237</xmin>
      <ymin>195</ymin>
      <xmax>341</xmax>
      <ymax>309</ymax>
    </bndbox>
  </object>
  </annotation>