<annotation>
  <folder>a</folder>
  <filename>d01b3756ba457890e882da3426079ffff885d412</filename>
  <path>C:\Users\priv_data4\Desktop\tt\a\d01b3756ba457890e882da3426079ffff885d412.jpg</path>
  <source>
    <database>Unknown</database>
  </source>
  <size>
    <width>737</width>
    <height>899</height>
    <depth>3</depth>
  </size>
  <segmented>0</segmented>
  <shape_type>RECT</shape_type>
  <object>
    <name>person</name>
    <pose>Unspecified</pose>
    <truncated>0</truncated>
    <difficult>0</difficult>
    <bndbox>
      <xmin>373</xmin>
      <ymin>119</ymin>
      <xmax>735</xmax>
      <ymax>837</ymax>
    </bndbox>
  </object>
  <object>
    <name>person</name>
    <pose>Unspecified</pose>
    <truncated>0</truncated>
    <difficult>0</difficult>
    <bndbox>
      <xmin>65</xmin>
      <ymin>49</ymin>
      <xmax>564</xmax>
      <ymax>794</ymax>
    </bndbox>
  </object>
  <object>
    <name>person</name>
    <pose>Unspecified</pose>
    <truncated>0</truncated>
    <difficult>0</difficult>
    <bndbox>
      <xmin>108</xmin>
      <ymin>79</ymin>
      <xmax>493</xmax>
      <ymax>843</ymax>
    </bndbox>
  </object>
  <object>
    <name>face</name>
    <pose>Unspecified</pose>
    <truncated>0</truncated>
    <difficult>0</difficult>
    <bndbox>
      <xmin>125</xmin>
      <ymin>105</ymin>
      <xmax>202</xmax>
      <ymax>189</ymax>
    </bndbox>
  </object>
  <object>
    <name>face</name>
    <pose>Unspecified</pose>
    <truncated>0</truncated>
    <difficult>0</difficult>
    <bndbox>
      <xmin>286</xmin>
      <ymin>116</ymin>
      <xmax>356</xmax>
      <ymax>216</ymax>
    </bndbox>
  </object>
  </annotation>