<annotation>
  <folder>a</folder>
  <filename>d965f03de7bf3f2b0482935f432230309f82ecfd</filename>
  <path>C:\Users\priv_data4\Desktop\tt\a\d965f03de7bf3f2b0482935f432230309f82ecfd.jpg</path>
  <source>
    <database>Unknown</database>
  </source>
  <size>
    <width>500</width>
    <height>330</height>
    <depth>3</depth>
  </size>
  <segmented>0</segmented>
  <shape_type>RECT</shape_type>
  <object>
    <name>person</name>
    <pose>Unspecified</pose>
    <truncated>0</truncated>
    <difficult>0</difficult>
    <bndbox>
      <xmin>205</xmin>
      <ymin>52</ymin>
      <xmax>409</xmax>
      <ymax>329</ymax>
    </bndbox>
  </object>
  <object>
    <name>person</name>
    <pose>Unspecified</pose>
    <truncated>0</truncated>
    <difficult>0</difficult>
    <bndbox>
      <xmin>32</xmin>
      <ymin>48</ymin>
      <xmax>219</xmax>
      <ymax>330</ymax>
    </bndbox>
  </object>
  <object>
    <name>face</name>
    <pose>Unspecified</pose>
    <truncated>0</truncated>
    <difficult>0</difficult>
    <bndbox>
      <xmin>143</xmin>
      <ymin>99</ymin>
      <xmax>204</xmax>
      <ymax>159</ymax>
    </bndbox>
  </object>
  <object>
    <name>face</name>
    <pose>Unspecified</pose>
    <truncated>0</truncated>
    <difficult>0</difficult>
    <bndbox>
      <xmin>228</xmin>
      <ymin>95</ymin>
      <xmax>293</xmax>
      <ymax>159</ymax>
    </bndbox>
  </object>
  </annotation>