<annotation>
  <folder>e</folder>
  <filename>d9862f973cf5cfdbe67fddbd3cf1e6de3f0096f6</filename>
  <path>C:\Users\priv_data2\Desktop\gy\e\d9862f973cf5cfdbe67fddbd3cf1e6de3f0096f6.jpg</path>
  <source>
    <database>Unknown</database>
  </source>
  <size>
    <width>650</width>
    <height>975</height>
    <depth>3</depth>
  </size>
  <segmented>0</segmented>
  <shape_type>RECT</shape_type>
  <object>
    <name>person</name>
    <pose>Unspecified</pose>
    <truncated>0</truncated>
    <difficult>0</difficult>
    <bndbox>
      <xmin>138</xmin>
      <ymin>17</ymin>
      <xmax>490</xmax>
      <ymax>967</ymax>
    </bndbox>
  </object>
  <object>
    <name>person</name>
    <pose>Unspecified</pose>
    <truncated>0</truncated>
    <difficult>0</difficult>
    <bndbox>
      <xmin>166</xmin>
      <ymin>1</ymin>
      <xmax>277</xmax>
      <ymax>181</ymax>
    </bndbox>
  </object>
  <object>
    <name>person</name>
    <pose>Unspecified</pose>
    <truncated>0</truncated>
    <difficult>0</difficult>
    <bndbox>
      <xmin>110</xmin>
      <ymin>1</ymin>
      <xmax>187</xmax>
      <ymax>239</ymax>
    </bndbox>
  </object>
  <object>
    <name>face</name>
    <pose>Unspecified</pose>
    <truncated>0</truncated>
    <difficult>0</difficult>
    <bndbox>
      <xmin>290</xmin>
      <ymin>49</ymin>
      <xmax>356</xmax>
      <ymax>145</ymax>
    </bndbox>
  </object>
  </annotation>