<annotation>
  <folder>c</folder>
  <filename>deadad56884b84e2df22440e2d9da1715f7f36ce</filename>
  <path>C:\Users\Administrator\Desktop\chm\c\deadad56884b84e2df22440e2d9da1715f7f36ce.jpg</path>
  <source>
    <database>Unknown</database>
  </source>
  <size>
    <width>550</width>
    <height>790</height>
    <depth>3</depth>
  </size>
  <segmented>0</segmented>
  <shape_type>RECT</shape_type>
  <object>
    <name>person</name>
    <pose>Unspecified</pose>
    <truncated>0</truncated>
    <difficult>0</difficult>
    <bndbox>
      <xmin>268</xmin>
      <ymin>66</ymin>
      <xmax>487</xmax>
      <ymax>776</ymax>
    </bndbox>
  </object>
  <object>
    <name>person</name>
    <pose>Unspecified</pose>
    <truncated>0</truncated>
    <difficult>0</difficult>
    <bndbox>
      <xmin>57</xmin>
      <ymin>16</ymin>
      <xmax>275</xmax>
      <ymax>785</ymax>
    </bndbox>
  </object>
  <object>
    <name>person</name>
    <pose>Unspecified</pose>
    <truncated>0</truncated>
    <difficult>0</difficult>
    <bndbox>
      <xmin>473</xmin>
      <ymin>144</ymin>
      <xmax>537</xmax>
      <ymax>337</ymax>
    </bndbox>
  </object>
  <object>
    <name>face</name>
    <pose>Unspecified</pose>
    <truncated>0</truncated>
    <difficult>0</difficult>
    <bndbox>
      <xmin>361</xmin>
      <ymin>99</ymin>
      <xmax>417</xmax>
      <ymax>173</ymax>
    </bndbox>
  </object>
  <object>
    <name>face</name>
    <pose>Unspecified</pose>
    <truncated>0</truncated>
    <difficult>0</difficult>
    <bndbox>
      <xmin>181</xmin>
      <ymin>54</ymin>
      <xmax>253</xmax>
      <ymax>135</ymax>
    </bndbox>
  </object>
</annotation>