<annotation>
  <folder>f</folder>
  <filename>e0faa249c9f7725cb43e99ec111777d629a89062</filename>
  <path>C:\Users\asus\Desktop\handface\f\e0faa249c9f7725cb43e99ec111777d629a89062.jpg</path>
  <source>
    <database>Unknown</database>
  </source>
  <size>
    <width>569</width>
    <height>850</height>
    <depth>3</depth>
  </size>
  <segmented>0</segmented>
  <shape_type>RECT</shape_type>
  <object>
    <name>person</name>
    <pose>Unspecified</pose>
    <truncated>0</truncated>
    <difficult>0</difficult>
    <bndbox>
      <xmin>416</xmin>
      <ymin>16</ymin>
      <xmax>755</xmax>
      <ymax>568</ymax>
    </bndbox>
  </object>
  <object>
    <name>person</name>
    <pose>Unspecified</pose>
    <truncated>0</truncated>
    <difficult>0</difficult>
    <bndbox>
      <xmin>212</xmin>
      <ymin>103</ymin>
      <xmax>415</xmax>
      <ymax>568</ymax>
    </bndbox>
  </object>
  <object>
    <name>face</name>
    <pose>Unspecified</pose>
    <truncated>0</truncated>
    <difficult>0</difficult>
    <bndbox>
      <xmin>284</xmin>
      <ymin>141</ymin>
      <xmax>346</xmax>
      <ymax>210</ymax>
    </bndbox>
  </object>
  <object>
    <name>face</name>
    <pose>Unspecified</pose>
    <truncated>0</truncated>
    <difficult>0</difficult>
    <bndbox>
      <xmin>521</xmin>
      <ymin>51</ymin>
      <xmax>595</xmax>
      <ymax>154</ymax>
    </bndbox>
  </object>
  <object>
    <name>person</name>
    <pose>Unspecified</pose>
    <truncated>0</truncated>
    <difficult>0</difficult>
    <bndbox>
      <xmin>801</xmin>
      <ymin>248</ymin>
      <xmax>850</xmax>
      <ymax>482</ymax>
    </bndbox>
  </object>
  <object>
    <name>face</name>
    <pose>Unspecified</pose>
    <truncated>0</truncated>
    <difficult>0</difficult>
    <bndbox>
      <xmin>836</xmin>
      <ymin>261</ymin>
      <xmax>850</xmax>
      <ymax>294</ymax>
    </bndbox>
  </object>
</annotation>