<annotation>
  <folder>b</folder>
  <filename>e76fa19fc619d3a016ffaa7f422a073de16229db</filename>
  <path>C:\Users\www\Desktop\xx\b\e76fa19fc619d3a016ffaa7f422a073de16229db.jpg</path>
  <source>
    <database>Unknown</database>
  </source>
  <size>
    <width>1000</width>
    <height>667</height>
    <depth>3</depth>
  </size>
  <segmented>0</segmented>
  <shape_type>RECT</shape_type>
  <object>
    <name>person</name>
    <pose>Unspecified</pose>
    <truncated>0</truncated>
    <difficult>0</difficult>
    <bndbox>
      <xmin>216</xmin>
      <ymin>104</ymin>
      <xmax>442</xmax>
      <ymax>873</ymax>
    </bndbox>
  </object>
  <object>
    <name>face</name>
    <pose>Unspecified</pose>
    <truncated>0</truncated>
    <difficult>0</difficult>
    <bndbox>
      <xmin>308</xmin>
      <ymin>136</ymin>
      <xmax>368</xmax>
      <ymax>216</ymax>
    </bndbox>
  </object>
  </annotation>