<annotation>
  <folder>e</folder>
  <filename>ea98c46f535107919ab27ea2cf77ec80e273c58e</filename>
  <path>C:\Users\priv_data2\Desktop\gy\e\ea98c46f535107919ab27ea2cf77ec80e273c58e.jpg</path>
  <source>
    <database>Unknown</database>
  </source>
  <size>
    <width>540</width>
    <height>781</height>
    <depth>3</depth>
  </size>
  <segmented>0</segmented>
  <shape_type>RECT</shape_type>
  <object>
    <name>person</name>
    <pose>Unspecified</pose>
    <truncated>0</truncated>
    <difficult>0</difficult>
    <bndbox>
      <xmin>123</xmin>
      <ymin>13</ymin>
      <xmax>523</xmax>
      <ymax>767</ymax>
    </bndbox>
  </object>
  <object>
    <name>face</name>
    <pose>Unspecified</pose>
    <truncated>0</truncated>
    <difficult>0</difficult>
    <bndbox>
      <xmin>266</xmin>
      <ymin>34</ymin>
      <xmax>336</xmax>
      <ymax>125</ymax>
    </bndbox>
  </object>
  </annotation>