<annotation>
  <folder>b</folder>
  <filename>ed83fba11dfdf9fae768f82ed346a928a5dc00a3</filename>
  <path>C:\Users\www\Desktop\xx\b\ed83fba11dfdf9fae768f82ed346a928a5dc00a3.jpg</path>
  <source>
    <database>Unknown</database>
  </source>
  <size>
    <width>773</width>
    <height>550</height>
    <depth>3</depth>
  </size>
  <segmented>0</segmented>
  <shape_type>RECT</shape_type>
  <object>
    <name>person</name>
    <pose>Unspecified</pose>
    <truncated>0</truncated>
    <difficult>0</difficult>
    <bndbox>
      <xmin>164</xmin>
      <ymin>3</ymin>
      <xmax>342</xmax>
      <ymax>756</ymax>
    </bndbox>
  </object>
  <object>
    <name>face</name>
    <pose>Unspecified</pose>
    <truncated>0</truncated>
    <difficult>0</difficult>
    <bndbox>
      <xmin>219</xmin>
      <ymin>54</ymin>
      <xmax>282</xmax>
      <ymax>115</ymax>
    </bndbox>
  </object>
  </annotation>