<annotation>
  <folder>facehand_error</folder>
  <filename>f7a8ae3c837801cb671ce65baa751210320b409a</filename>
  <path>C:\Users\priv_data4\Desktop\facehand_error\facehand_error\f7a8ae3c837801cb671ce65baa751210320b409a.jpg</path>
  <source>
    <database>Unknown</database>
  </source>
  <size>
    <width>550</width>
    <height>825</height>
    <depth>3</depth>
  </size>
  <segmented>0</segmented>
  <shape_type>RECT</shape_type>
  <object>
    <name>person</name>
    <pose>Unspecified</pose>
    <truncated>0</truncated>
    <difficult>0</difficult>
    <bndbox>
      <xmin>169</xmin>
      <ymin>8</ymin>
      <xmax>408</xmax>
      <ymax>814</ymax>
    </bndbox>
  </object>
  <object>
    <name>face</name>
    <pose>Unspecified</pose>
    <truncated>0</truncated>
    <difficult>0</difficult>
    <bndbox>
      <xmin>253</xmin>
      <ymin>42</ymin>
      <xmax>310</xmax>
      <ymax>117</ymax>
    </bndbox>
  </object>
  <object>
    <name>person</name>
    <pose>Unspecified</pose>
    <truncated>0</truncated>
    <difficult>0</difficult>
    <bndbox>
      <xmin>114</xmin>
      <ymin>1</ymin>
      <xmax>229</xmax>
      <ymax>257</ymax>
    </bndbox>
  </object>
  <object>
    <name>person</name>
    <pose>Unspecified</pose>
    <truncated>0</truncated>
    <difficult>0</difficult>
    <bndbox>
      <xmin>1</xmin>
      <ymin>144</ymin>
      <xmax>72</xmax>
      <ymax>505</ymax>
    </bndbox>
  </object>
</annotation>